runwayapi/__init__.py
runwayapi/main.py
runwayapi/response.py
runwayapi-0.2.1.dist-info/METADATA
runwayapi-0.2.1.dist-info/WHEEL
runwayapi-0.2.1.dist-info/top_level.txt
runwayapi-0.2.1.dist-info/RECORD
