Metadata-Version: 2.4
Name: runwayapi
Version: 0.2.1
Requires-Python: >=3.7
Requires-Dist: requests>=2.31.0
Requires-Dist: pydantic>=2.0.0
Requires-Dist: typing-extensions>=4.5.0
Dynamic: requires-dist
Dynamic: requires-python
